{"content": {"suites": {"0": {"status": {"total_pass": 0, "total_skip": 0, "total_xpass": 0, "total_xfail": 0, "total_rerun": 0, "total_fail": 3, "total_error": 0}, "tests": {"0": {"status": "FAIL", "message": "   selenium.common.exceptions.TimeoutException: Message: \n   Stacktrace:\n   0   chromedriver                        0x0000000102be2004 chromedriver + 4169732\n   1   chromedriver                        0x0000000102bd9ff8 chromedriver + 4136952\n   2   chromedriver                        0x000000010282f500 chromedriver + 292096\n   3   chromedriver                        0x00000001028747a0 chromedriver + 575392\n   4   chromedriver                        0x00000001028af818 chromedriver + 817176\n   5   chromedriver                        0x00000001028685e8 chromedriver + 525800\n   6   chromedriver                        0x00000001028694b8 chromedriver + 529592\n   7   chromedriver                        0x0000000102ba8334 chromedriver + 3932980\n   8   chromedriver                        0x0000000102bac970 chromedriver + 3950960\n   9   chromedriver                        0x0000000102b90774 chromedriver + 3835764\n   10  chromedriver                        0x0000000102bad478 chromedriver + 3953784\n   11  chromedriver                        0x0000000102b82ab4 chromedriver + 3779252\n   12  chromedriver                        0x0000000102bc9914 chromedriver + 4069652\n   13  chromedriver                        0x0000000102bc9a90 chromedriver + 4070032\n   14  chromedriver                        0x0000000102bd9c70 chromedriver + 4136048\n   15  libsystem_pthread.dylib             0x0000000192b97fa8 _pthread_start + 148\n   16  libsystem_pthread.dylib             0x0000000192b92da0 thread_start + 8\n", "test_name": "test_login", "rerun": "0"}, "1": {"status": "FAIL", "message": "   selenium.common.exceptions.NoSuchElementException: Message: no such element: Unable to locate element: {\"method\":\"css selector\",\"selector\":\".todayBest\"}\n     (Session info: chrome=119.0.6045.159)\n   Stacktrace:\n   0   chromedriver                        0x0000000102be2004 chromedriver + 4169732\n   1   chromedriver                        0x0000000102bd9ff8 chromedriver + 4136952\n   2   chromedriver                        0x000000010282f500 chromedriver + 292096\n   3   chromedriver                        0x00000001028747a0 chromedriver + 575392\n   4   chromedriver                        0x00000001028af818 chromedriver + 817176\n   5   chromedriver                        0x00000001028685e8 chromedriver + 525800\n   6   chromedriver                        0x00000001028694b8 chromedriver + 529592\n   7   chromedriver                        0x0000000102ba8334 chromedriver + 3932980\n   8   chromedriver                        0x0000000102bac970 chromedriver + 3950960\n   9   chromedriver                        0x0000000102b90774 chromedriver + 3835764\n   10  chromedriver                        0x0000000102bad478 chromedriver + 3953784\n   11  chromedriver                        0x0000000102b82ab4 chromedriver + 3779252\n   12  chromedriver                        0x0000000102bc9914 chromedriver + 4069652\n   13  chromedriver                        0x0000000102bc9a90 chromedriver + 4070032\n   14  chromedriver                        0x0000000102bd9c70 chromedriver + 4136048\n   15  libsystem_pthread.dylib             0x0000000192b97fa8 _pthread_start + 148\n   16  libsystem_pthread.dylib             0x0000000192b92da0 thread_start + 8\n", "test_name": "test_searchpopular", "rerun": "0"}, "2": {"status": "FAIL", "message": "   selenium.common.exceptions.NoSuchWindowException: Message: no such window: target window already closed\n   from unknown error: web view not found\n     (Session info: chrome=119.0.6045.159)\n   Stacktrace:\n   0   chromedriver                        0x0000000102be2004 chromedriver + 4169732\n   1   chromedriver                        0x0000000102bd9ff8 chromedriver + 4136952\n   2   chromedriver                        0x000000010282f500 chromedriver + 292096\n   3   chromedriver                        0x00000001028082d8 chromedriver + 131800\n   4   chromedriver                        0x000000010289bf68 chromedriver + 737128\n   5   chromedriver                        0x00000001028aefac chromedriver + 815020\n   6   chromedriver                        0x00000001028685e8 chromedriver + 525800\n   7   chromedriver                        0x00000001028694b8 chromedriver + 529592\n   8   chromedriver                        0x0000000102ba8334 chromedriver + 3932980\n   9   chromedriver                        0x0000000102bac970 chromedriver + 3950960\n   10  chromedriver                        0x0000000102b90774 chromedriver + 3835764\n   11  chromedriver                        0x0000000102bad478 chromedriver + 3953784\n   12  chromedriver                        0x0000000102b82ab4 chromedriver + 3779252\n   13  chromedriver                        0x0000000102bc9914 chromedriver + 4069652\n   14  chromedriver                        0x0000000102bc9a90 chromedriver + 4070032\n   15  chromedriver                        0x0000000102bd9c70 chromedriver + 4136048\n   16  libsystem_pthread.dylib             0x0000000192b97fa8 _pthread_start + 148\n   17  libsystem_pthread.dylib             0x0000000192b92da0 thread_start + 8\n", "test_name": "test_searchlocal", "rerun": "0"}}, "suite_name": "test_web.py"}}}, "date": "March 18, 2024", "start_time": 1710755845.629627, "total_suite": 1, "status": "FAIL", "status_list": {"pass": "0", "fail": "3", "skip": "0", "error": "0", "xpass": "0", "xfail": "0", "rerun": "0"}, "total_tests": "3"}